bsvlib/__init__.py
bsvlib/aes.py
bsvlib/base58.py
bsvlib/constants.py
bsvlib/curve.py
bsvlib/hash.py
bsvlib/keys.py
bsvlib/utils.py
bsvlib/wallet.py
bsvlib/hd/__init__.py
bsvlib/hd/bip32.py
bsvlib/hd/bip39.py
bsvlib/hd/bip44.py
bsvlib/hd/wordlist/chinese_simplified.txt
bsvlib/hd/wordlist/english.txt
bsvlib/script/__init__.py
bsvlib/script/script.py
bsvlib/script/type.py
bsvlib/service/__init__.py
bsvlib/service/provider.py
bsvlib/service/service.py
bsvlib/service/whatsonchain.py
bsvlib/transaction/__init__.py
bsvlib/transaction/transaction.py
bsvlib/transaction/unspent.py
bsvlib-0.10.0.dist-info/LICENSE
bsvlib-0.10.0.dist-info/METADATA
bsvlib-0.10.0.dist-info/WHEEL
bsvlib-0.10.0.dist-info/top_level.txt
bsvlib-0.10.0.dist-info/RECORD
