Metadata-Version: 2.1
Name: bsvlib
Version: 0.10.0
Summary: Bitcoin SV (BSV) Python Library
Home-page: https://github.com/gitzhou/bsvlib
Author: aaron67
Author-email: aaron67@aaron67.cc
Project-URL: Bug Tracker, https://github.com/gitzhou/bsvlib/issues
Keywords: bsv,bitcoin-sv,bitcoin sv,bitcoinsv,cryptocurrency,payments,tools,wallet
Classifier: Intended Audience :: Developers
Classifier: Intended Audience :: End Users/Desktop
Classifier: Programming Language :: Python :: 3.7
Classifier: Programming Language :: Python :: 3.8
Classifier: Programming Language :: Python :: 3.9
Classifier: Programming Language :: Python :: 3.10
Classifier: License :: OSI Approved :: MIT License
Classifier: Operating System :: OS Independent
Requires-Python: >=3.7
License-File: LICENSE
Requires-Dist: requests
Requires-Dist: typing-extensions
Requires-Dist: pycryptodomex
Requires-Dist: coincurve
